AUTHORS
BUGS.md
CHANGES.rst
LICENSE
MANIFEST.in
README.rst
TODO.md
setup.py
taskmg/__init__.py
taskmg.egg-info/PKG-INFO
taskmg.egg-info/SOURCES.txt
taskmg.egg-info/dependency_links.txt
taskmg.egg-info/entry_points.txt
taskmg.egg-info/requires.txt
taskmg.egg-info/top_level.txt
taskmg/qt/__init__.py
taskmg/qt/main.py
taskmg/qt/widgets/__init__.py
taskmg/qt/widgets/mainwindow.py
taskmg/qt/widgets/tabs/__init__.py
taskmg/qt/widgets/tabs/task.py
taskmg/qt/widgets/tabs/tracker.py