Metadata-Version: 1.2
Name: taskmg
Version: 1.0.dev0
Summary: A task manager
Home-page: https://github.com/jeremiedecock/taskmg
Author: Jeremie DECOCK
Author-email: jd.jdhp@gmail.com
Maintainer: Jeremie DECOCK
Maintainer-email: jd.jdhp@gmail.com
License: UNKNOWN
Download-URL: https://github.com/jeremiedecock/taskmg
Keywords: task manager
Platform: UNKNOWN
Classifier: Development Status :: 4 - Beta
Classifier: License :: OSI Approved :: MIT License
Classifier: Natural Language :: English
Classifier: Operating System :: OS Independent
Classifier: Programming Language :: Python :: 3
Classifier: Topic :: Documentation
